{
  "datadir": "/Users/red/lworkspace/lightec/daemon/daemon/node/test/testnet/.daemon",
  "network": "testnet",
  "rpcbind": "127.0.0.1",
  "rpcport": "8970",
  "wsPort": "8880",
  "btcUser": "lightec",
  "btcPwd": "Abcd1234",
  "btcUrl": "http://18.116.118.39:18332",
  "ethUrl": "http://18.119.98.31:8545",
  "beaconUrl": "http://18.119.98.31:30814",
  "oasisUrl": "https://testnet.sapphire.oasis.dev",
  "discordHookUrl": "",
  "ethPrivateKey": "c0781e4ca498e0ad693751bac014c0ab00c2841f28903e59cdfe1ab212438e49",
  "btcInitHeight": 2865725,
  "btcGenesisHeight": 2865725,
  "ethInitHeight": 1809284,
  "enableLocalWorker": true,
  "beaconInitSlot": 2170880,
  "autoSubmit": true,
  "disableRecursiveAgent": false,
  "disableTxAgent": false
}